{
    "Номер": "3809",
    "ФИО": "ВАЛЕРИЯ",
    "Имя": "Валерия",
    "Части_ФИО": [
        {
            "NUM": "1",
            "Часть": "имя",
            "Значение": "Валерия",
            "Тип": "монашеское"
        }
    ],
    "Сан_ЦеркСлужение": "монахиня",
    "Пол": "Жен",
    "Кончина": {
        "Год": "1937",
        "Текст": "Дата кончины."
    },
    "События": [
        {
            "NUM": "1",
            "Тип": "служение",
            "Текст": "Подвизалась в Касимовском Казанском монастыре Рязанской епархии.",
            "Монастыри": [
                {
                    "NUM": "1",
                    "Название": "Касимовский Казанский монастырь Рязанской епархии."
                }
            ],
            "Источники": [
                {
                    "NUM": "1",
                    "Название": "Список репрессированных священнослужителей и мирян по Рязанской епархии."
                }
            ]
        },
        {
            "NUM": "2",
            "Тип": "арест",
            "Текст": "Репрессирована.",
            "Источники": [
                {
                    "NUM": "1",
                    "Название": "Список репрессированных священнослужителей и мирян по Рязанской епархии."
                }
            ]
        },
        {
            "NUM": "3",
            "Тип": "кончина",
            "Датировка": "1937",
            "Текст": "Дата кончины.",
            "Год_начала": "1937",
            "Источники": [
                {
                    "NUM": "1",
                    "Название": "Список репрессированных священнослужителей и мирян по Рязанской епархии."
                }
            ],
            "Поисковые_даты": [
                {
                    "NUM": "1",
                    "Начало_мин": "1937-01-01",
                    "Начало_макс": "1937-12-31",
                    "Окончание_мин": "1937-01-01",
                    "Окончание_макс": "1937-12-31",
                    "Длина_интервала": "365"
                }
            ]
        }
    ],
    "Библиография": [
        {
            "NUM": "1",
            "Название": "Список репрессированных священнослужителей и мирян по Рязанской епархии.",
            "Тип": "публикация"
        }
    ]
}